graph_embeddings/__init__.py
graph_embeddings/_version.py
graph_embeddings/algorithms/__init__.py
graph_embeddings/algorithms/node2vec.py
graph_embeddings/algorithms/utils.py
graph_embeddings/algorithms/tests/__init__.py
graph_embeddings/algorithms/tests/test_node2vec.py
graph_embeddings/algorithms/tests/test_utils.py
graph_embeddings-0.1.0.dist-info/LICENSE
graph_embeddings-0.1.0.dist-info/METADATA
graph_embeddings-0.1.0.dist-info/WHEEL
graph_embeddings-0.1.0.dist-info/top_level.txt
graph_embeddings-0.1.0.dist-info/RECORD
