Metadata-Version: 2.1
Name: graph-embeddings
Version: 0.1.0
Summary: Graph embeddings for downstream tasks
Home-page: https://github.com/rodrigo-arenas/Graph-Embeddings
Author: Rodrigo Arenas
Author-email: rodrigo.arenas456@gmail.com
License: MIT
Project-URL: Documentation, https://graph-embeddings.readthedocs.io/
Project-URL: Source Code, https://github.com/rodrigo-arenas/Graph-Embeddings
Project-URL: Bug Tracker, https://github.com/rodrigo-arenas/Graph-Embeddings/issues
Platform: UNKNOWN
Classifier: License :: OSI Approved :: MIT License
Classifier: Development Status :: 4 - Beta
Classifier: Programming Language :: Python :: 3
Classifier: Programming Language :: Python :: 3.8
Requires-Python: >=3.8
License-File: LICENSE
Requires-Dist: networkx (>=2.8.4)
Requires-Dist: stellargraph (>=1.2.1)
Requires-Dist: chardet (>=5.0.0)
Requires-Dist: tqdm (>=4.64.0)
